Py4ti2int64_cc.cpython-311-darwin.so
Py4ti2gmp.py
Py4ti2int64.py
Py4ti2int32.py
Py4ti2int32_cc.cpython-311-darwin.so
Py4ti2gmp_cc.cpython-311-darwin.so
py4ti2-0.5.1.dist-info/RECORD
py4ti2-0.5.1.dist-info/WHEEL
py4ti2-0.5.1.dist-info/top_level.txt
py4ti2-0.5.1.dist-info/METADATA
py4ti2-0.5.1.dist-info/licenses/LICENSE
py4ti2.dylibs/libgmpxx.4.dylib
py4ti2.dylibs/libglpk.40.dylib
py4ti2.dylibs/lib4ti2common.0.dylib
py4ti2.dylibs/lib4ti2int64.0.dylib
py4ti2.dylibs/lib4ti2gmp.0.dylib
py4ti2.dylibs/libzsolve.0.dylib
py4ti2.dylibs/lib4ti2int32.0.dylib
py4ti2.dylibs/libgmp.10.dylib
