Metadata-Version: 2.4
Name: Py4ti2
Version: 0.5.1
Summary: An interface to some 4ti2 functions
Author-email: "Alfredo Sanchez-R.-Navarro" <alfredo.sanchez@uca.es>
License-Expression: GPL-2.0-only
Project-URL: Homepage, https://github.com/alfsan/Py4ti2
Requires-Python: >=3.9
License-File: LICENSE
Dynamic: license-file
